{
    "cars": [
        {
            "id": 1,
            "car_name": "toyota",
            "details": [
                {
                    "model_name": "corolla",
                    "year": "2018"
                }
            ],
            "price": "2,500,000",
            "imageURL": "https://via.placeholder.com/300x250.png"
        },
        {
            "id": 2,
            "car_name": "mazda",
            "details": [
                {
                    "model_name": "corolla",
                    "year": "2017"
                }
            ],
            "price": "2,500,000",
            "imageURL": "https://via.placeholder.com/300x250.png"
        },
        {
            "id": 3,
            "car_name": "benz",
            "details": [
                {
                    "model_name": "camry",
                    "year": "2018"
                }
            ],
            "price": "2,500,000",
            "imageURL": "https://via.placeholder.com/300x250.png"
        },
        {
            "id": 4,
            "car_name": "range",
            "details": [
                {
                    "model_name": "camry",
                    "year": "2018"
                }
            ],
            "price": "2,500,000",
            "imageURL": "https://via.placeholder.com/300x250.png"
        }
    ]
}